scrape_jobs/__init__.py
scrape_jobs/config.py
scrape_jobs/program.py
scrape_jobs/runner.py
scrape_jobs/sample_config.ini
scrape_jobs/base/__init__.py
scrape_jobs/base/data_collection.py
scrape_jobs/base/data_processing.py
scrape_jobs/base/data_storage.py
scrape_jobs/cli/__init__.py
scrape_jobs/cli/config_initializer.py
scrape_jobs/cli/jobs_scraper.py
scrape_jobs/linkedin/__init__.py
scrape_jobs/linkedin/linkedin_config.py
scrape_jobs/linkedin/linkedin_job.py
scrape_jobs/linkedin/linkedin_page.py
scrape_jobs/seek/__init__.py
scrape_jobs/seek/seek_config.py
scrape_jobs/seek/seek_job.py
scrape_jobs/seek/seek_page.py
scrape_jobs-3.0.2.dist-info/AUTHORS.rst
scrape_jobs-3.0.2.dist-info/LICENSE.txt
scrape_jobs-3.0.2.dist-info/METADATA
scrape_jobs-3.0.2.dist-info/WHEEL
scrape_jobs-3.0.2.dist-info/entry_points.txt
scrape_jobs-3.0.2.dist-info/top_level.txt
scrape_jobs-3.0.2.dist-info/RECORD
