Metadata-Version: 2.1
Name: scrape-jobs
Version: 3.0.2
Summary: CLI jobs scraper targeting multiple sites
Home-page: https://github.com/Hrissimir/scrape_jobs
Author: Hrissimir
Author-email: hrisimir.dakov@gmail.com
License: mit
Project-URL: Code, https://github.com/Hrissimir/scrape_jobs
Platform: any
Classifier: Development Status :: 4 - Beta
Classifier: Programming Language :: Python
Requires-Python: >=3.6
Requires-Dist: hed-utils (==4.1.2)
Provides-Extra: testing
Requires-Dist: coverage (==5.0) ; extra == 'testing'
Requires-Dist: flake8 (==3.7.9) ; extra == 'testing'
Requires-Dist: pylint (==2.4.4) ; extra == 'testing'
Requires-Dist: pytest (==5.3.2) ; extra == 'testing'
Requires-Dist: pytest-cov (==2.8.1) ; extra == 'testing'
Requires-Dist: pyscaffold[all] (==3.2.3) ; extra == 'testing'
Requires-Dist: twine (==3.1.1) ; extra == 'testing'
